[1,["1ac1370cc@6c48a"],["_textureSource"],["cc.SpriteFrame"],0,[[[{"name":"BT_start1","rect":{"x":131,"y":3,"width":316,"height":100},"offset":{"x":0,"y":0.5},"originalSize":{"width":374,"height":117},"rotated":false,"capInsets":[0,0,0,0],"packable":true,"pixelsToUnit":100,"pivot":{"x":0.5,"y":0.5},"meshType":0}],[0],0,[0],[0],[0]],[[{"name":"start2","rect":{"x":131,"y":109,"width":316,"height":100},"offset":{"x":0,"y":0.5},"originalSize":{"width":374,"height":117},"rotated":false,"capInsets":[0,0,0,0],"packable":true,"pixelsToUnit":100,"pivot":{"x":0.5,"y":0.5},"meshType":0}],[0],0,[0],[0],[0]],[[{"name":"bt_atom_d","rect":{"x":453,"y":157,"width":132,"height":132},"offset":{"x":0,"y":0},"originalSize":{"width":132,"height":132},"rotated":false,"capInsets":[0,0,0,0],"packable":true,"pixelsToUnit":100,"pivot":{"x":0.5,"y":0.5},"meshType":0}],[0],0,[0],[0],[0]],[[{"name":"win_bg1","rect":{"x":591,"y":291,"width":84,"height":84},"offset":{"x":0,"y":0},"originalSize":{"width":84,"height":84},"rotated":false,"capInsets":[18,18,18,18],"packable":true,"pixelsToUnit":100,"pivot":{"x":0.5,"y":0.5},"meshType":0}],[0],0,[0],[0],[0]],[[{"name":"UI_atom","rect":{"x":385,"y":921,"width":93,"height":99},"offset":{"x":-0.5,"y":0.5},"originalSize":{"width":100,"height":100},"rotated":false,"capInsets":[0,0,0,0],"packable":true,"pixelsToUnit":100,"pivot":{"x":0.5,"y":0.5},"meshType":0}],[0],0,[0],[0],[0]],[[{"name":"game_over","rect":{"x":3,"y":3,"width":706,"height":107},"offset":{"x":3,"y":5.5},"originalSize":{"width":730,"height":120},"rotated":true,"capInsets":[0,0,0,0],"packable":true,"pixelsToUnit":100,"pivot":{"x":0.5,"y":0.5},"meshType":0}],[0],0,[0],[0],[0]],[[{"name":"bt_atom_e","rect":{"x":453,"y":295,"width":132,"height":132},"offset":{"x":0,"y":0},"originalSize":{"width":132,"height":132},"rotated":false,"capInsets":[0,0,0,0],"packable":true,"pixelsToUnit":100,"pivot":{"x":0.5,"y":0.5},"meshType":0}],[0],0,[0],[0],[0]],[[{"name":"pause_e","rect":{"x":484,"y":921,"width":98,"height":98},"offset":{"x":1,"y":-1},"originalSize":{"width":100,"height":100},"rotated":false,"capInsets":[0,0,0,0],"packable":true,"pixelsToUnit":100,"pivot":{"x":0.5,"y":0.5},"meshType":0}],[0],0,[0],[0],[0]],[[{"name":"bt_to_right","rect":{"x":588,"y":815,"width":90,"height":88},"offset":{"x":0,"y":0},"originalSize":{"width":100,"height":100},"rotated":false,"capInsets":[0,0,0,0],"packable":true,"pixelsToUnit":100,"pivot":{"x":0.5,"y":0.5},"meshType":0}],[0],0,[0],[0],[0]],[[{"name":"UI_scoreBG","rect":{"x":607,"y":3,"width":282,"height":62},"offset":{"x":-2,"y":0},"originalSize":{"width":286,"height":62},"rotated":true,"capInsets":[0,0,0,0],"packable":true,"pixelsToUnit":100,"pivot":{"x":0.5,"y":0.5},"meshType":0}],[0],0,[0],[0],[0]],[[{"name":"pause_d","rect":{"x":385,"y":815,"width":100,"height":98},"offset":{"x":0,"y":-1},"originalSize":{"width":100,"height":100},"rotated":true,"capInsets":[0,0,0,0],"packable":true,"pixelsToUnit":100,"pivot":{"x":0.5,"y":0.5},"meshType":0}],[0],0,[0],[0],[0]],[[{"name":"UI_shield","rect":{"x":591,"y":381,"width":84,"height":82},"offset":{"x":0,"y":0},"originalSize":{"width":84,"height":82},"rotated":false,"capInsets":[0,0,0,0],"packable":true,"pixelsToUnit":100,"pivot":{"x":0.5,"y":0.5},"meshType":0}],[0],0,[0],[0],[0]],[[{"name":"BT_start2","rect":{"x":131,"y":215,"width":316,"height":100},"offset":{"x":0,"y":0.5},"originalSize":{"width":374,"height":117},"rotated":false,"capInsets":[0,0,0,0],"packable":true,"pixelsToUnit":100,"pivot":{"x":0.5,"y":0.5},"meshType":0}],[0],0,[0],[0],[0]],[[{"name":"audio_e","rect":{"x":385,"y":709,"width":100,"height":100},"offset":{"x":0,"y":0},"originalSize":{"width":100,"height":100},"rotated":false,"capInsets":[0,0,0,0],"packable":true,"pixelsToUnit":100,"pivot":{"x":0.5,"y":0.5},"meshType":0}],[0],0,[0],[0],[0]],[[{"name":"audio_d","rect":{"x":491,"y":709,"width":100,"height":100},"offset":{"x":0,"y":0},"originalSize":{"width":100,"height":100},"rotated":false,"capInsets":[0,0,0,0],"packable":true,"pixelsToUnit":100,"pivot":{"x":0.5,"y":0.5},"meshType":0}],[0],0,[0],[0],[0]],[[{"name":"home_d","rect":{"x":588,"y":909,"width":90,"height":88},"offset":{"x":0,"y":0},"originalSize":{"width":100,"height":100},"rotated":false,"capInsets":[0,0,0,0],"packable":true,"pixelsToUnit":100,"pivot":{"x":0.5,"y":0.5},"meshType":0}],[0],0,[0],[0],[0]],[[{"name":"bt_shield_e","rect":{"x":453,"y":433,"width":132,"height":132},"offset":{"x":0,"y":0},"originalSize":{"width":132,"height":132},"rotated":false,"capInsets":[0,0,0,0],"packable":true,"pixelsToUnit":100,"pivot":{"x":0.5,"y":0.5},"meshType":0}],[0],0,[0],[0],[0]],[[{"name":"best_score","rect":{"x":116,"y":639,"width":90,"height":54},"offset":{"x":0,"y":-1.5},"originalSize":{"width":90,"height":57},"rotated":false,"capInsets":[36,0,36,0],"packable":true,"pixelsToUnit":100,"pivot":{"x":0.5,"y":0.5},"meshType":0}],[0],0,[0],[0],[0]],[[{"name":"end_game2","rect":{"x":131,"y":321,"width":316,"height":100},"offset":{"x":0,"y":0.5},"originalSize":{"width":374,"height":117},"rotated":false,"capInsets":[0,0,0,0],"packable":true,"pixelsToUnit":100,"pivot":{"x":0.5,"y":0.5},"meshType":0}],[0],0,[0],[0],[0]],[[{"name":"UI_score","rect":{"x":453,"y":3,"width":148,"height":148},"offset":{"x":0,"y":0},"originalSize":{"width":150,"height":150},"rotated":false,"capInsets":[0,0,0,0],"packable":true,"pixelsToUnit":100,"pivot":{"x":0.5,"y":0.5},"meshType":0}],[0],0,[0],[0],[0]],[[{"name":"home_e","rect":{"x":489,"y":815,"width":90,"height":88},"offset":{"x":0,"y":0},"originalSize":{"width":100,"height":100},"rotated":false,"capInsets":[0,0,0,0],"packable":true,"pixelsToUnit":100,"pivot":{"x":0.5,"y":0.5},"meshType":0}],[0],0,[0],[0],[0]],[[{"name":"UI_bullet","rect":{"x":131,"y":699,"width":248,"height":269},"offset":{"x":3,"y":0.5},"originalSize":{"width":300,"height":300},"rotated":false,"capInsets":[0,0,0,0],"packable":true,"pixelsToUnit":100,"pivot":{"x":0.5,"y":0.5},"meshType":0}],[0],0,[0],[0],[0]],[[{"name":"start1","rect":{"x":131,"y":427,"width":316,"height":100},"offset":{"x":0,"y":0.5},"originalSize":{"width":374,"height":117},"rotated":false,"capInsets":[0,0,0,0],"packable":true,"pixelsToUnit":100,"pivot":{"x":0.5,"y":0.5},"meshType":0}],[0],0,[0],[0],[0]],[[{"name":"end_game1","rect":{"x":131,"y":533,"width":316,"height":100},"offset":{"x":0,"y":0.5},"originalSize":{"width":374,"height":117},"rotated":false,"capInsets":[0,0,0,0],"packable":true,"pixelsToUnit":100,"pivot":{"x":0.5,"y":0.5},"meshType":0}],[0],0,[0],[0],[0]],[[{"name":"bt_shield_d","rect":{"x":453,"y":571,"width":132,"height":132},"offset":{"x":0,"y":0},"originalSize":{"width":132,"height":132},"rotated":false,"capInsets":[0,0,0,0],"packable":true,"pixelsToUnit":100,"pivot":{"x":0.5,"y":0.5},"meshType":0}],[0],0,[0],[0],[0]],[[{"name":"UI_shell","rect":{"x":3,"y":715,"width":122,"height":284},"offset":{"x":5,"y":0},"originalSize":{"width":290,"height":288},"rotated":false,"capInsets":[0,0,0,0],"packable":true,"pixelsToUnit":100,"pivot":{"x":0.5,"y":0.5},"meshType":0}],[0],0,[0],[0],[0]]]]
